{"version":2,"kind":"Notebook","sha256":"48448f5ad3f72df8499808712d0290985c6f463cdb31550f3e30e5d7eeb1d92c","slug":"notebooks.summary.comparison","location":"/notebooks/summary/comparison.ipynb","dependencies":[],"frontmatter":{"title":"Comparison of Demonstration Models","content_includes_title":true,"kernelspec":{"name":"python3","display_name":"Python 3 (ipykernel)","language":"python"},"authors":[{"nameParsed":{"literal":"Project Pythia Community","given":"Project Pythia","family":"Community"},"name":"Project Pythia Community","url":"https://projectpythia.org/","id":"contributors-myst-generated-uid-0"}],"open_access":true,"license":{"content":{"id":"Apache-2.0","url":"https://opensource.org/licenses/Apache-2.0","name":"Apache License 2.0","free":true,"osi":true},"code":{"id":"CC-BY-4.0","url":"https://creativecommons.org/licenses/by/4.0/","name":"Creative Commons Attribution 4.0 International","free":true,"CC":true}},"github":"https://github.com/projectpythia/atmos-modeling-cookbook","copyright":"2024","numbering":{"title":{"offset":1}},"edit_url":"https://github.com/projectpythia/atmos-modeling-cookbook/blob/HEAD/notebooks/summary/comparison.ipynb","exports":[{"format":"ipynb","filename":"comparison.ipynb","url":"/atmos-modeling-cookbook/build/comparison-5235340763cd5cf239092bd357af2d97.ipynb"}]},"widgets":{},"mdast":{"type":"root","children":[{"type":"block","kind":"notebook-content","children":[{"type":"paragraph","position":{"start":{"line":1,"column":1},"end":{"line":1,"column":1}},"children":[{"type":"text","value":"Let’s start here! If you can directly link to an image relevant to your notebook, such as ","position":{"start":{"line":1,"column":1},"end":{"line":1,"column":1}},"key":"KzDTfDeFY4"},{"type":"link","url":"https://github.com/numpy/numpy/blob/main/doc/source/_static/numpylogo.svg","position":{"start":{"line":1,"column":1},"end":{"line":1,"column":1}},"children":[{"type":"text","value":"canonical logos","position":{"start":{"line":1,"column":1},"end":{"line":1,"column":1}},"key":"TrOzeFqcA0"}],"urlSource":"https://github.com/numpy/numpy/blob/main/doc/source/_static/numpylogo.svg","data":{"kind":"file","org":"numpy","repo":"numpy","reference":"main","file":"doc/source/_static/numpylogo.svg","raw":"https://raw.githubusercontent.com/numpy/numpy/main/doc/source/_static/numpylogo.svg"},"internal":false,"protocol":"github","key":"NiyqFT5YXt"},{"type":"text","value":", do so here at the top of your notebook. You can do this with Markdown syntax,","position":{"start":{"line":1,"column":1},"end":{"line":1,"column":1}},"key":"ZR4GzJpj9Y"}],"key":"y9idMdpuZS"},{"type":"blockquote","position":{"start":{"line":3,"column":1},"end":{"line":3,"column":1}},"children":[{"type":"paragraph","position":{"start":{"line":3,"column":1},"end":{"line":3,"column":1}},"children":[{"type":"inlineCode","value":"![<image title>](http://link.com/to/image.png \"image alt text\")","position":{"start":{"line":3,"column":1},"end":{"line":3,"column":1}},"key":"qsR3QDiqwF"}],"key":"g4Dn7Z6v33"}],"key":"cODindeFSW"},{"type":"paragraph","position":{"start":{"line":5,"column":1},"end":{"line":5,"column":1}},"children":[{"type":"text","value":"or edit this cell to see raw HTML ","position":{"start":{"line":5,"column":1},"end":{"line":5,"column":1}},"key":"qkd7cEIJJK"},{"type":"inlineCode","value":"img","position":{"start":{"line":5,"column":1},"end":{"line":5,"column":1}},"key":"CSs1n5EaVz"},{"type":"text","value":" demonstration. This is preferred if you need to shrink your embedded image. ","position":{"start":{"line":5,"column":1},"end":{"line":5,"column":1}},"key":"cMqmXRZbu4"},{"type":"strong","position":{"start":{"line":5,"column":1},"end":{"line":5,"column":1}},"children":[{"type":"text","value":"Either way be sure to include ","position":{"start":{"line":5,"column":1},"end":{"line":5,"column":1}},"key":"Mpq5dVZ5ka"},{"type":"inlineCode","value":"alt","position":{"start":{"line":5,"column":1},"end":{"line":5,"column":1}},"key":"Lqf8PUIuvd"},{"type":"text","value":" text for any embedded images to make your content more accessible.","position":{"start":{"line":5,"column":1},"end":{"line":5,"column":1}},"key":"nts1ZO6NQZ"}],"key":"LDHkVtZAmx"}],"key":"ID40AJihfb"},{"type":"paragraph","position":{"start":{"line":7,"column":1},"end":{"line":7,"column":1}},"children":[{"type":"image","url":"/myst_assets_folderimages/ProjectPythia_Logo_Final-01-Blue.svg","alt":"Project Pythia Logo","key":"WNp1vELWxE"}],"key":"m045hETkO3"}],"key":"PLWp1YaXEN"},{"type":"block","kind":"notebook-content","children":[{"type":"heading","depth":1,"position":{"start":{"line":1,"column":1},"end":{"line":1,"column":1}},"children":[{"type":"text","value":"Comparison of Demonstration Models","position":{"start":{"line":1,"column":1},"end":{"line":1,"column":1}},"key":"bnr8Bz43Vu"}],"identifier":"comparison-of-demonstration-models","label":"Comparison of Demonstration Models","html_id":"comparison-of-demonstration-models","implicit":true,"key":"yS5kbcCh6b"},{"type":"paragraph","position":{"start":{"line":3,"column":1},"end":{"line":3,"column":1}},"children":[{"type":"text","value":"Next, title your notebook appropriately with a top-level Markdown header, ","position":{"start":{"line":3,"column":1},"end":{"line":3,"column":1}},"key":"bsLrVv3Tuj"},{"type":"inlineCode","value":"#","position":{"start":{"line":3,"column":1},"end":{"line":3,"column":1}},"key":"ziyCAATrLK"},{"type":"text","value":". Do not use this level header anywhere else in the notebook. Our book build process will use this title in the navbar, table of contents, etc. Keep it short, keep it descriptive. Follow this with a ","position":{"start":{"line":3,"column":1},"end":{"line":3,"column":1}},"key":"QnuqQIOQY2"},{"type":"inlineCode","value":"---","position":{"start":{"line":3,"column":1},"end":{"line":3,"column":1}},"key":"HmT82xgEAT"},{"type":"text","value":" cell to visually distinguish the transition to the prerequisites section.","position":{"start":{"line":3,"column":1},"end":{"line":3,"column":1}},"key":"iYIlfR8jvQ"}],"key":"cuGZObHZuD"}],"key":"L8cJHnilQO"},{"type":"block","kind":"notebook-content","children":[{"type":"thematicBreak","position":{"start":{"line":1,"column":1},"end":{"line":1,"column":1}},"key":"WuH4ozZfMR"}],"key":"ib8f8coZro"},{"type":"block","kind":"notebook-content","children":[{"type":"heading","depth":2,"position":{"start":{"line":1,"column":1},"end":{"line":1,"column":1}},"children":[{"type":"text","value":"Overview","position":{"start":{"line":1,"column":1},"end":{"line":1,"column":1}},"key":"uCdJmF6Cqg"}],"identifier":"overview","label":"Overview","html_id":"overview","implicit":true,"key":"hvMQFh6M8e"},{"type":"paragraph","position":{"start":{"line":2,"column":1},"end":{"line":2,"column":1}},"children":[{"type":"text","value":"If you have an introductory paragraph, lead with it here! Keep it short and tied to your material, then be sure to continue into the required list of topics below,","position":{"start":{"line":2,"column":1},"end":{"line":2,"column":1}},"key":"KTaYyY4C1w"}],"key":"iy50pYgIjc"},{"type":"list","ordered":true,"start":1,"spread":false,"position":{"start":{"line":4,"column":1},"end":{"line":8,"column":1}},"children":[{"type":"listItem","spread":true,"position":{"start":{"line":4,"column":1},"end":{"line":4,"column":1}},"children":[{"type":"text","value":"This is a numbered list of the specific topics","position":{"start":{"line":4,"column":1},"end":{"line":4,"column":1}},"key":"UDHsbVFqO6"}],"key":"TsZjC1ekHG"},{"type":"listItem","spread":true,"position":{"start":{"line":5,"column":1},"end":{"line":5,"column":1}},"children":[{"type":"text","value":"These should map approximately to your main sections of content","position":{"start":{"line":5,"column":1},"end":{"line":5,"column":1}},"key":"uSbKLHwYRw"}],"key":"ukN0Og4hzS"},{"type":"listItem","spread":true,"position":{"start":{"line":6,"column":1},"end":{"line":6,"column":1}},"children":[{"type":"text","value":"Or each second-level, ","position":{"start":{"line":6,"column":1},"end":{"line":6,"column":1}},"key":"SPgulL5DfJ"},{"type":"inlineCode","value":"##","position":{"start":{"line":6,"column":1},"end":{"line":6,"column":1}},"key":"gLWktvhcpc"},{"type":"text","value":", header in your notebook","position":{"start":{"line":6,"column":1},"end":{"line":6,"column":1}},"key":"PqzSuNIzv0"}],"key":"EuKwK1dtf5"},{"type":"listItem","spread":true,"position":{"start":{"line":7,"column":1},"end":{"line":7,"column":1}},"children":[{"type":"text","value":"Keep the size and scope of your notebook in check","position":{"start":{"line":7,"column":1},"end":{"line":7,"column":1}},"key":"aO94Fh16xy"}],"key":"EaqrlLnyyf"},{"type":"listItem","spread":true,"position":{"start":{"line":8,"column":1},"end":{"line":8,"column":1}},"children":[{"type":"text","value":"And be sure to let the reader know up front the important concepts they’ll be leaving with","position":{"start":{"line":8,"column":1},"end":{"line":8,"column":1}},"key":"BchR8eUzQC"}],"key":"N2bmwBUVim"}],"key":"BqcoVMvMvh"}],"key":"oW7MNdEjTx"},{"type":"block","kind":"notebook-content","children":[{"type":"heading","depth":2,"position":{"start":{"line":1,"column":1},"end":{"line":1,"column":1}},"children":[{"type":"text","value":"Prerequisites","position":{"start":{"line":1,"column":1},"end":{"line":1,"column":1}},"key":"GQqVTi00gF"}],"identifier":"prerequisites","label":"Prerequisites","html_id":"prerequisites","implicit":true,"key":"wRXlyFQA0G"},{"type":"paragraph","position":{"start":{"line":2,"column":1},"end":{"line":2,"column":1}},"children":[{"type":"text","value":"This section was inspired by ","position":{"start":{"line":2,"column":1},"end":{"line":2,"column":1}},"key":"qr7552cBmQ"},{"type":"link","url":"https://github.com/alan-turing-institute/the-turing-way/blob/master/book/templates/chapter-template/chapter-landing-page.md","position":{"start":{"line":2,"column":1},"end":{"line":2,"column":1}},"children":[{"type":"text","value":"this template","position":{"start":{"line":2,"column":1},"end":{"line":2,"column":1}},"key":"TsXW02WdVY"}],"urlSource":"https://github.com/alan-turing-institute/the-turing-way/blob/master/book/templates/chapter-template/chapter-landing-page.md","data":{"kind":"file","org":"alan-turing-institute","repo":"the-turing-way","reference":"master","file":"book/templates/chapter-template/chapter-landing-page.md","raw":"https://raw.githubusercontent.com/alan-turing-institute/the-turing-way/master/book/templates/chapter-template/chapter-landing-page.md"},"internal":false,"protocol":"github","key":"NWIbw28HQi"},{"type":"text","value":" of the wonderful ","position":{"start":{"line":2,"column":1},"end":{"line":2,"column":1}},"key":"Xwz61DSZu0"},{"type":"link","url":"https://the-turing-way.netlify.app","position":{"start":{"line":2,"column":1},"end":{"line":2,"column":1}},"children":[{"type":"text","value":"The Turing Way","position":{"start":{"line":2,"column":1},"end":{"line":2,"column":1}},"key":"ddLZD01Cs0"}],"urlSource":"https://the-turing-way.netlify.app","key":"i9ardoiQjh"},{"type":"text","value":" Jupyter Book.","position":{"start":{"line":2,"column":1},"end":{"line":2,"column":1}},"key":"UMIc25PoW0"}],"key":"sRa8JkufBp"},{"type":"paragraph","position":{"start":{"line":4,"column":1},"end":{"line":4,"column":1}},"children":[{"type":"text","value":"Following your overview, tell your reader what concepts, packages, or other background information they’ll ","position":{"start":{"line":4,"column":1},"end":{"line":4,"column":1}},"key":"is6Zj61ySm"},{"type":"strong","position":{"start":{"line":4,"column":1},"end":{"line":4,"column":1}},"children":[{"type":"text","value":"need","position":{"start":{"line":4,"column":1},"end":{"line":4,"column":1}},"key":"tyvB3kbCVb"}],"key":"Fd8up7qSnH"},{"type":"text","value":" before learning your material. Tie this explicitly with links to other pages here in Foundations or to relevant external resources. Remove this body text, then populate the Markdown table, denoted in this cell with ","position":{"start":{"line":4,"column":1},"end":{"line":4,"column":1}},"key":"KNI5T8w8G1"},{"type":"inlineCode","value":"|","position":{"start":{"line":4,"column":1},"end":{"line":4,"column":1}},"key":"YJNpDTf5xy"},{"type":"text","value":" vertical brackets, below, and fill out the information following. In this table, lay out prerequisite concepts by explicitly linking to other Foundations material or external resources, or describe generally helpful concepts.","position":{"start":{"line":4,"column":1},"end":{"line":4,"column":1}},"key":"P7i49fTjOc"}],"key":"q5SocrJoFa"},{"type":"paragraph","position":{"start":{"line":6,"column":1},"end":{"line":6,"column":1}},"children":[{"type":"text","value":"Label the importance of each concept explicitly as ","position":{"start":{"line":6,"column":1},"end":{"line":6,"column":1}},"key":"ZOx2m4Adpy"},{"type":"strong","position":{"start":{"line":6,"column":1},"end":{"line":6,"column":1}},"children":[{"type":"text","value":"helpful/necessary","position":{"start":{"line":6,"column":1},"end":{"line":6,"column":1}},"key":"NLxsfk20IU"}],"key":"kj4PLUHViq"},{"type":"text","value":".","position":{"start":{"line":6,"column":1},"end":{"line":6,"column":1}},"key":"rxBbxGP2Lq"}],"key":"B3qyoV9qIj"},{"type":"table","position":{"start":{"line":8,"column":1},"end":{"line":12,"column":1}},"children":[{"type":"tableRow","position":{"start":{"line":8,"column":1},"end":{"line":8,"column":1}},"children":[{"type":"tableCell","header":true,"position":{"start":{"line":8,"column":1},"end":{"line":8,"column":1}},"children":[{"type":"text","value":"Concepts","position":{"start":{"line":8,"column":1},"end":{"line":8,"column":1}},"key":"RL9yhPepvX"}],"key":"xulVMvZTff"},{"type":"tableCell","header":true,"position":{"start":{"line":8,"column":1},"end":{"line":8,"column":1}},"children":[{"type":"text","value":"Importance","position":{"start":{"line":8,"column":1},"end":{"line":8,"column":1}},"key":"rGDovGHnoU"}],"key":"VZGcZDs27z"},{"type":"tableCell","header":true,"position":{"start":{"line":8,"column":1},"end":{"line":8,"column":1}},"children":[{"type":"text","value":"Notes","position":{"start":{"line":8,"column":1},"end":{"line":8,"column":1}},"key":"oxZq3HkNDD"}],"key":"I2HgDFx5K2"}],"key":"Mz6s9ATPaZ"},{"type":"tableRow","position":{"start":{"line":10,"column":1},"end":{"line":10,"column":1}},"children":[{"type":"tableCell","position":{"start":{"line":10,"column":1},"end":{"line":10,"column":1}},"children":[{"type":"link","url":"https://foundations.projectpythia.org/core/cartopy/cartopy.html","position":{"start":{"line":10,"column":1},"end":{"line":10,"column":1}},"children":[{"type":"text","value":"Intro to Cartopy","position":{"start":{"line":10,"column":1},"end":{"line":10,"column":1}},"key":"xW2B17QaMA"}],"urlSource":"https://foundations.projectpythia.org/core/cartopy/cartopy.html","key":"cZ3TXL4vbj"}],"key":"ImDwoUsZSL"},{"type":"tableCell","position":{"start":{"line":10,"column":1},"end":{"line":10,"column":1}},"children":[{"type":"text","value":"Necessary","position":{"start":{"line":10,"column":1},"end":{"line":10,"column":1}},"key":"Ee2jJJPX69"}],"key":"kJYnlxN4sE"},{"type":"tableCell","position":{"start":{"line":10,"column":1},"end":{"line":10,"column":1}},"children":[],"key":"fDa1cZ6BST"}],"key":"emm0MHZq8P"},{"type":"tableRow","position":{"start":{"line":11,"column":1},"end":{"line":11,"column":1}},"children":[{"type":"tableCell","position":{"start":{"line":11,"column":1},"end":{"line":11,"column":1}},"children":[{"type":"link","url":"https://foundations.projectpythia.org/core/data-formats/netcdf-cf.html","position":{"start":{"line":11,"column":1},"end":{"line":11,"column":1}},"children":[{"type":"text","value":"Understanding of NetCDF","position":{"start":{"line":11,"column":1},"end":{"line":11,"column":1}},"key":"HdsZBGYiKp"}],"urlSource":"https://foundations.projectpythia.org/core/data-formats/netcdf-cf.html","key":"XdK8dIFfLl"}],"key":"bpAHuEV5XC"},{"type":"tableCell","position":{"start":{"line":11,"column":1},"end":{"line":11,"column":1}},"children":[{"type":"text","value":"Helpful","position":{"start":{"line":11,"column":1},"end":{"line":11,"column":1}},"key":"oI2IzDFiBD"}],"key":"KxMg9QLPdW"},{"type":"tableCell","position":{"start":{"line":11,"column":1},"end":{"line":11,"column":1}},"children":[{"type":"text","value":"Familiarity with metadata structure","position":{"start":{"line":11,"column":1},"end":{"line":11,"column":1}},"key":"HaqkL3GNPt"}],"key":"MWkDRt4OHO"}],"key":"Ry13kStzN9"},{"type":"tableRow","position":{"start":{"line":12,"column":1},"end":{"line":12,"column":1}},"children":[{"type":"tableCell","position":{"start":{"line":12,"column":1},"end":{"line":12,"column":1}},"children":[{"type":"text","value":"Project management","position":{"start":{"line":12,"column":1},"end":{"line":12,"column":1}},"key":"NYOaQSeCSf"}],"key":"f31OWFmMOq"},{"type":"tableCell","position":{"start":{"line":12,"column":1},"end":{"line":12,"column":1}},"children":[{"type":"text","value":"Helpful","position":{"start":{"line":12,"column":1},"end":{"line":12,"column":1}},"key":"uTCLNapBaP"}],"key":"gKL0d2Jtbl"},{"type":"tableCell","position":{"start":{"line":12,"column":1},"end":{"line":12,"column":1}},"children":[],"key":"bNSd0L3eY1"}],"key":"EAhzTx5L7I"}],"key":"alZh3TJO7u"},{"type":"list","ordered":false,"spread":false,"position":{"start":{"line":14,"column":1},"end":{"line":18,"column":1}},"children":[{"type":"listItem","spread":true,"position":{"start":{"line":14,"column":1},"end":{"line":14,"column":1}},"children":[{"type":"strong","position":{"start":{"line":14,"column":1},"end":{"line":14,"column":1}},"children":[{"type":"text","value":"Time to learn","position":{"start":{"line":14,"column":1},"end":{"line":14,"column":1}},"key":"CNgccgHzjx"}],"key":"BqzSZVn7OR"},{"type":"text","value":": estimate in minutes. For a rough idea, use 5 mins per subsection, 10 if longer; add these up for a total. Safer to round up and overestimate.","position":{"start":{"line":14,"column":1},"end":{"line":14,"column":1}},"key":"OnnkIGEXrr"}],"key":"LdOuYknbcR"},{"type":"listItem","spread":true,"position":{"start":{"line":15,"column":1},"end":{"line":18,"column":1}},"children":[{"type":"strong","position":{"start":{"line":15,"column":1},"end":{"line":15,"column":1}},"children":[{"type":"text","value":"System requirements","position":{"start":{"line":15,"column":1},"end":{"line":15,"column":1}},"key":"vGfdmqJPkk"}],"key":"p5x8BFjPcR"},{"type":"text","value":":","position":{"start":{"line":15,"column":1},"end":{"line":15,"column":1}},"key":"zvB8I8yChO"},{"type":"list","ordered":false,"spread":false,"position":{"start":{"line":16,"column":1},"end":{"line":18,"column":1}},"children":[{"type":"listItem","spread":true,"position":{"start":{"line":16,"column":1},"end":{"line":16,"column":1}},"children":[{"type":"text","value":"Populate with any system, version, or non-Python software requirements if necessary","position":{"start":{"line":16,"column":1},"end":{"line":16,"column":1}},"key":"RoMQcR4Fls"}],"key":"jIHrdugEDu"},{"type":"listItem","spread":true,"position":{"start":{"line":17,"column":1},"end":{"line":17,"column":1}},"children":[{"type":"text","value":"Otherwise use the concepts table above and the Imports section below to describe required packages as necessary","position":{"start":{"line":17,"column":1},"end":{"line":17,"column":1}},"key":"rwXNd24iNY"}],"key":"yahiWgoGUk"},{"type":"listItem","spread":true,"position":{"start":{"line":18,"column":1},"end":{"line":18,"column":1}},"children":[{"type":"text","value":"If no extra requirements, remove the ","position":{"start":{"line":18,"column":1},"end":{"line":18,"column":1}},"key":"urzTnYAzR7"},{"type":"strong","position":{"start":{"line":18,"column":1},"end":{"line":18,"column":1}},"children":[{"type":"text","value":"System requirements","position":{"start":{"line":18,"column":1},"end":{"line":18,"column":1}},"key":"czLUCwjBJU"}],"key":"tCZwrHZBBQ"},{"type":"text","value":" point altogether","position":{"start":{"line":18,"column":1},"end":{"line":18,"column":1}},"key":"w0QHAtL6fv"}],"key":"vDI1nz2a0C"}],"key":"yoUodL1Hp2"}],"key":"vTA4jhN0D6"}],"key":"EeLJYK9uPb"}],"key":"vWGDFPe5Vk"},{"type":"block","kind":"notebook-content","children":[{"type":"thematicBreak","position":{"start":{"line":1,"column":1},"end":{"line":1,"column":1}},"key":"Qq5yTSCql1"}],"key":"a5f6nXwGqm"},{"type":"block","kind":"notebook-content","children":[{"type":"heading","depth":2,"position":{"start":{"line":1,"column":1},"end":{"line":1,"column":1}},"children":[{"type":"text","value":"Imports","position":{"start":{"line":1,"column":1},"end":{"line":1,"column":1}},"key":"UPG3RgRket"}],"identifier":"imports","label":"Imports","html_id":"imports","implicit":true,"key":"RppzRjM8nn"},{"type":"paragraph","position":{"start":{"line":2,"column":1},"end":{"line":2,"column":1}},"children":[{"type":"text","value":"Begin your body of content with another ","position":{"start":{"line":2,"column":1},"end":{"line":2,"column":1}},"key":"VWhdGncZqG"},{"type":"inlineCode","value":"---","position":{"start":{"line":2,"column":1},"end":{"line":2,"column":1}},"key":"xydYft8GQG"},{"type":"text","value":" divider before continuing into this section, then remove this body text and populate the following code cell with all necessary Python imports ","position":{"start":{"line":2,"column":1},"end":{"line":2,"column":1}},"key":"nuXCDYimMh"},{"type":"strong","position":{"start":{"line":2,"column":1},"end":{"line":2,"column":1}},"children":[{"type":"text","value":"up-front","position":{"start":{"line":2,"column":1},"end":{"line":2,"column":1}},"key":"TiJHb8Spw6"}],"key":"OGzcdx9ct7"},{"type":"text","value":":","position":{"start":{"line":2,"column":1},"end":{"line":2,"column":1}},"key":"Xffkj2nki4"}],"key":"gTNOD2Hmug"}],"key":"vnKz8A9gyi"},{"type":"block","kind":"notebook-code","children":[{"type":"code","lang":"python","executable":true,"value":"import sys","key":"IE0LHrOCtN"},{"type":"output","id":"kU5R-kLCfp1Cm1JFMbzMj","data":[],"key":"m6Fn0VRl0b"}],"key":"jWrdqh3M6F"},{"type":"block","kind":"notebook-content","children":[{"type":"heading","depth":2,"position":{"start":{"line":1,"column":1},"end":{"line":1,"column":1}},"children":[{"type":"text","value":"Your first content section","position":{"start":{"line":1,"column":1},"end":{"line":1,"column":1}},"key":"XuHjcp7co9"}],"identifier":"your-first-content-section","label":"Your first content section","html_id":"your-first-content-section","implicit":true,"key":"CkbF4cUmnU"}],"key":"ZvNugkTUHL"},{"type":"block","kind":"notebook-content","children":[{"type":"paragraph","position":{"start":{"line":1,"column":1},"end":{"line":1,"column":1}},"children":[{"type":"text","value":"This is where you begin your first section of material, loosely tied to your objectives stated up front. Tie together your notebook as a narrative, with interspersed Markdown text, images, and more as necessary,","position":{"start":{"line":1,"column":1},"end":{"line":1,"column":1}},"key":"xIUyPkaicu"}],"key":"bjXlqrkV87"}],"key":"UpNf8BuOBm"},{"type":"block","kind":"notebook-code","children":[{"type":"code","lang":"python","executable":true,"value":"# as well as any and all of your code cells\nprint(\"Hello world!\")","key":"CJ2lirfw4W"},{"type":"output","id":"DeuRgPa2PkgbVNkU5ZHaw","data":[{"output_type":"stream","name":"stdout","text":"Hello world!\n"}],"key":"fCgRkZY54j"}],"key":"eusHIB7rHQ"},{"type":"block","kind":"notebook-content","children":[{"type":"heading","depth":3,"position":{"start":{"line":1,"column":1},"end":{"line":1,"column":1}},"children":[{"type":"text","value":"A content subsection","position":{"start":{"line":1,"column":1},"end":{"line":1,"column":1}},"key":"nRSRKyUlsH"}],"identifier":"a-content-subsection","label":"A content subsection","html_id":"a-content-subsection","implicit":true,"key":"BwIL8ttClI"},{"type":"paragraph","position":{"start":{"line":2,"column":1},"end":{"line":2,"column":1}},"children":[{"type":"text","value":"Divide and conquer your objectives with Markdown subsections, which will populate the helpful navbar in Jupyter Lab and here on the Jupyter Book!","position":{"start":{"line":2,"column":1},"end":{"line":2,"column":1}},"key":"dn2hqYH7C9"}],"key":"XiJPiSglYL"}],"key":"ny2Pg9uAoL"},{"type":"block","kind":"notebook-code","children":[{"type":"code","lang":"python","executable":true,"value":"# some subsection code\nnew = \"helpful information\"","key":"VdWl09aXeO"},{"type":"output","id":"5a885VL4H6IWdNpz_hHY5","data":[],"key":"JCpaZrr6lP"}],"key":"s0UEPqhXBW"},{"type":"block","kind":"notebook-content","children":[{"type":"heading","depth":3,"position":{"start":{"line":1,"column":1},"end":{"line":1,"column":1}},"children":[{"type":"text","value":"Another content subsection","position":{"start":{"line":1,"column":1},"end":{"line":1,"column":1}},"key":"mULJzYTS0e"}],"identifier":"another-content-subsection","label":"Another content subsection","html_id":"another-content-subsection","implicit":true,"key":"VhlO3dLWbo"},{"type":"paragraph","position":{"start":{"line":2,"column":1},"end":{"line":2,"column":1}},"children":[{"type":"text","value":"Keep up the good work! A note, ","position":{"start":{"line":2,"column":1},"end":{"line":2,"column":1}},"key":"RfBGuDp6SQ"},{"type":"emphasis","position":{"start":{"line":2,"column":1},"end":{"line":2,"column":1}},"children":[{"type":"text","value":"try to avoid using code comments as narrative","position":{"start":{"line":2,"column":1},"end":{"line":2,"column":1}},"key":"Uy2663fWua"}],"key":"i3Qjh2mn0o"},{"type":"text","value":", and instead let them only exist as brief clarifications where necessary.","position":{"start":{"line":2,"column":1},"end":{"line":2,"column":1}},"key":"Uktabnianu"}],"key":"h1SUy3vcXg"}],"key":"k81jGPU3RF"},{"type":"block","kind":"notebook-content","children":[{"type":"heading","depth":2,"position":{"start":{"line":1,"column":1},"end":{"line":1,"column":1}},"children":[{"type":"text","value":"Your second content section","position":{"start":{"line":1,"column":1},"end":{"line":1,"column":1}},"key":"BuBwSJBsiq"}],"identifier":"your-second-content-section","label":"Your second content section","html_id":"your-second-content-section","implicit":true,"key":"hsxZv0dzXA"},{"type":"paragraph","position":{"start":{"line":2,"column":1},"end":{"line":2,"column":1}},"children":[{"type":"text","value":"Here we can move on to our second objective, and we can demonstrate","position":{"start":{"line":2,"column":1},"end":{"line":2,"column":1}},"key":"RIsfl8vrhD"}],"key":"rCzEj6XXco"}],"key":"bTdpTqIdId"},{"type":"block","kind":"notebook-content","children":[{"type":"heading","depth":3,"position":{"start":{"line":1,"column":1},"end":{"line":1,"column":1}},"children":[{"type":"text","value":"Subsection to the second section","position":{"start":{"line":1,"column":1},"end":{"line":1,"column":1}},"key":"Sv0bcjxrDu"}],"identifier":"subsection-to-the-second-section","label":"Subsection to the second section","html_id":"subsection-to-the-second-section","implicit":true,"key":"K2DRWn3OZZ"},{"type":"heading","depth":4,"position":{"start":{"line":3,"column":1},"end":{"line":3,"column":1}},"children":[{"type":"text","value":"a quick demonstration","position":{"start":{"line":3,"column":1},"end":{"line":3,"column":1}},"key":"WR0Y1LsF55"}],"identifier":"a-quick-demonstration","label":"a quick demonstration","html_id":"a-quick-demonstration","implicit":true,"key":"R3n363nOZV"},{"type":"heading","depth":5,"position":{"start":{"line":5,"column":1},"end":{"line":5,"column":1}},"children":[{"type":"text","value":"of further and further","position":{"start":{"line":5,"column":1},"end":{"line":5,"column":1}},"key":"j85xUlbXDV"}],"identifier":"of-further-and-further","label":"of further and further","html_id":"of-further-and-further","implicit":true,"key":"cZ3JEJw0io"},{"type":"heading","depth":6,"position":{"start":{"line":7,"column":1},"end":{"line":7,"column":1}},"children":[{"type":"text","value":"header levels","position":{"start":{"line":7,"column":1},"end":{"line":7,"column":1}},"key":"iLZJdmdhry"}],"identifier":"header-levels","label":"header levels","html_id":"header-levels","implicit":true,"key":"y1rZxJ2Fjr"}],"key":"ZVFklXrZsj"},{"type":"block","kind":"notebook-content","children":[{"type":"paragraph","position":{"start":{"line":1,"column":1},"end":{"line":1,"column":1}},"children":[{"type":"text","value":"as well ","position":{"start":{"line":1,"column":1},"end":{"line":1,"column":1}},"key":"OvsJSGJk6q"},{"type":"inlineMath","value":"m = a * t / h","position":{"start":{"line":1,"column":1},"end":{"line":1,"column":1}},"html":"<span class=\"katex\"><span class=\"katex-mathml\"><math xmlns=\"http://www.w3.org/1998/Math/MathML\"><semantics><mrow><mi>m</mi><mo>=</mo><mi>a</mi><mo>∗</mo><mi>t</mi><mi mathvariant=\"normal\">/</mi><mi>h</mi></mrow><annotation encoding=\"application/x-tex\">m = a * t / h</annotation></semantics></math></span><span class=\"katex-html\" aria-hidden=\"true\"><span class=\"base\"><span class=\"strut\" style=\"height:0.4306em;\"></span><span class=\"mord mathnormal\">m</span><span class=\"mspace\" style=\"margin-right:0.2778em;\"></span><span class=\"mrel\">=</span><span class=\"mspace\" style=\"margin-right:0.2778em;\"></span></span><span class=\"base\"><span class=\"strut\" style=\"height:0.4653em;\"></span><span class=\"mord mathnormal\">a</span><span class=\"mspace\" style=\"margin-right:0.2222em;\"></span><span class=\"mbin\">∗</span><span class=\"mspace\" style=\"margin-right:0.2222em;\"></span></span><span class=\"base\"><span class=\"strut\" style=\"height:1em;vertical-align:-0.25em;\"></span><span class=\"mord mathnormal\">t</span><span class=\"mord\">/</span><span class=\"mord mathnormal\">h</span></span></span></span>","key":"lt0jLY4Ke9"},{"type":"text","value":" text! Similarly, you have access to other ","position":{"start":{"line":1,"column":1},"end":{"line":1,"column":1}},"key":"FWxbH6OM5U"},{"type":"inlineMath","value":"\\LaTeX","position":{"start":{"line":1,"column":1},"end":{"line":1,"column":1}},"html":"<span class=\"katex\"><span class=\"katex-mathml\"><math xmlns=\"http://www.w3.org/1998/Math/MathML\"><semantics><mrow><mtext>LaTeX</mtext></mrow><annotation encoding=\"application/x-tex\">\\LaTeX</annotation></semantics></math></span><span class=\"katex-html\" aria-hidden=\"true\"><span class=\"base\"><span class=\"strut\" style=\"height:0.8988em;vertical-align:-0.2155em;\"></span><span class=\"mord text\"><span class=\"mord textrm\">L</span><span class=\"mspace\" style=\"margin-right:-0.36em;\"></span><span class=\"vlist-t\"><span class=\"vlist-r\"><span class=\"vlist\" style=\"height:0.6833em;\"><span style=\"top:-2.905em;\"><span class=\"pstrut\" style=\"height:2.7em;\"></span><span class=\"mord\"><span class=\"mord textrm mtight sizing reset-size6 size3\">A</span></span></span></span></span></span><span class=\"mspace\" style=\"margin-right:-0.15em;\"></span><span class=\"mord text\"><span class=\"mord textrm\">T</span><span class=\"mspace\" style=\"margin-right:-0.1667em;\"></span><span class=\"vlist-t vlist-t2\"><span class=\"vlist-r\"><span class=\"vlist\" style=\"height:0.4678em;\"><span style=\"top:-2.7845em;\"><span class=\"pstrut\" style=\"height:3em;\"></span><span class=\"mord\"><span class=\"mord textrm\">E</span></span></span></span><span class=\"vlist-s\">​</span></span><span class=\"vlist-r\"><span class=\"vlist\" style=\"height:0.2155em;\"><span></span></span></span></span><span class=\"mspace\" style=\"margin-right:-0.125em;\"></span><span class=\"mord textrm\">X</span></span></span></span></span></span>","key":"mOXu1eqIDt"},{"type":"text","value":" equation ","position":{"start":{"line":1,"column":1},"end":{"line":1,"column":1}},"key":"RxcyIoamO0"},{"type":"link","url":"https://jupyter-notebook.readthedocs.io/en/stable/examples/Notebook/Typesetting%20Equations.html","position":{"start":{"line":1,"column":1},"end":{"line":1,"column":1}},"children":[{"type":"strong","position":{"start":{"line":1,"column":1},"end":{"line":1,"column":1}},"children":[{"type":"text","value":"functionality","position":{"start":{"line":1,"column":1},"end":{"line":1,"column":1}},"key":"U6AvKBRSGa"}],"key":"ZRWNlVV1fy"}],"urlSource":"https://jupyter-notebook.readthedocs.io/en/stable/examples/Notebook/Typesetting%20Equations.html","key":"RWmzwUryYY"},{"type":"text","value":" via MathJax (demo below from link),","position":{"start":{"line":1,"column":1},"end":{"line":1,"column":1}},"key":"JEo0VDVPi5"}],"key":"xgZQAgi1j8"},{"type":"math","value":"\\begin{align}\n\\dot{x} & = \\sigma(y-x) \\\\\n\\dot{y} & = \\rho x - y - xz \\\\\n\\dot{z} & = -\\beta z + xy\n\\end{align}","position":{"start":{"line":3,"column":1},"end":{"line":6,"column":1}},"html":"<span class=\"katex-display\"><span class=\"katex\"><span class=\"katex-mathml\"><math xmlns=\"http://www.w3.org/1998/Math/MathML\" display=\"block\"><semantics><mtable rowspacing=\"0.25em\" columnalign=\"right left\" columnspacing=\"0em\"><mtr><mtd class =\"mtr-glue\"></mtd><mtd><mstyle scriptlevel=\"0\" displaystyle=\"true\"><mover accent=\"true\"><mi>x</mi><mo>˙</mo></mover></mstyle></mtd><mtd><mstyle scriptlevel=\"0\" displaystyle=\"true\"><mrow><mrow></mrow><mo>=</mo><mi>σ</mi><mo stretchy=\"false\">(</mo><mi>y</mi><mo>−</mo><mi>x</mi><mo stretchy=\"false\">)</mo></mrow></mstyle></mtd><mtd class =\"mtr-glue\"></mtd><mtd class =\"mml-eqn-num\"></mtd></mtr><mtr><mtd class =\"mtr-glue\"></mtd><mtd><mstyle scriptlevel=\"0\" displaystyle=\"true\"><mover accent=\"true\"><mi>y</mi><mo>˙</mo></mover></mstyle></mtd><mtd><mstyle scriptlevel=\"0\" displaystyle=\"true\"><mrow><mrow></mrow><mo>=</mo><mi>ρ</mi><mi>x</mi><mo>−</mo><mi>y</mi><mo>−</mo><mi>x</mi><mi>z</mi></mrow></mstyle></mtd><mtd class =\"mtr-glue\"></mtd><mtd class =\"mml-eqn-num\"></mtd></mtr><mtr><mtd class =\"mtr-glue\"></mtd><mtd><mstyle scriptlevel=\"0\" displaystyle=\"true\"><mover accent=\"true\"><mi>z</mi><mo>˙</mo></mover></mstyle></mtd><mtd><mstyle scriptlevel=\"0\" displaystyle=\"true\"><mrow><mrow></mrow><mo>=</mo><mo>−</mo><mi>β</mi><mi>z</mi><mo>+</mo><mi>x</mi><mi>y</mi></mrow></mstyle></mtd><mtd class =\"mtr-glue\"></mtd><mtd class =\"mml-eqn-num\"></mtd></mtr></mtable><annotation encoding=\"application/x-tex\">\\begin{align}\n\\dot{x} &amp; = \\sigma(y-x) \\\\\n\\dot{y} &amp; = \\rho x - y - xz \\\\\n\\dot{z} &amp; = -\\beta z + xy\n\\end{align}</annotation></semantics></math></span><span class=\"katex-html\" aria-hidden=\"true\"><span class=\"base\"><span class=\"strut\" style=\"height:4.5em;vertical-align:-2em;\"></span><span class=\"mtable\"><span class=\"col-align-r\"><span class=\"vlist-t vlist-t2\"><span class=\"vlist-r\"><span class=\"vlist\" style=\"height:2.5em;\"><span style=\"top:-4.66em;\"><span class=\"pstrut\" style=\"height:3em;\"></span><span class=\"mord\"><span class=\"mord accent\"><span class=\"vlist-t\"><span class=\"vlist-r\"><span class=\"vlist\" style=\"height:0.6679em;\"><span style=\"top:-3em;\"><span class=\"pstrut\" style=\"height:3em;\"></span><span class=\"mord mathnormal\">x</span></span><span style=\"top:-3em;\"><span class=\"pstrut\" style=\"height:3em;\"></span><span class=\"accent-body\" style=\"left:-0.1111em;\"><span class=\"mord\">˙</span></span></span></span></span></span></span></span></span><span style=\"top:-3.16em;\"><span class=\"pstrut\" style=\"height:3em;\"></span><span class=\"mord\"><span class=\"mord accent\"><span class=\"vlist-t vlist-t2\"><span class=\"vlist-r\"><span class=\"vlist\" style=\"height:0.6679em;\"><span style=\"top:-3em;\"><span class=\"pstrut\" style=\"height:3em;\"></span><span class=\"mord mathnormal\" style=\"margin-right:0.03588em;\">y</span></span><span style=\"top:-3em;\"><span class=\"pstrut\" style=\"height:3em;\"></span><span class=\"accent-body\" style=\"left:-0.0833em;\"><span class=\"mord\">˙</span></span></span></span><span class=\"vlist-s\">​</span></span><span class=\"vlist-r\"><span class=\"vlist\" style=\"height:0.1944em;\"><span></span></span></span></span></span></span></span><span style=\"top:-1.66em;\"><span class=\"pstrut\" style=\"height:3em;\"></span><span class=\"mord\"><span class=\"mord accent\"><span class=\"vlist-t\"><span class=\"vlist-r\"><span class=\"vlist\" style=\"height:0.6679em;\"><span style=\"top:-3em;\"><span class=\"pstrut\" style=\"height:3em;\"></span><span class=\"mord mathnormal\" style=\"margin-right:0.04398em;\">z</span></span><span style=\"top:-3em;\"><span class=\"pstrut\" style=\"height:3em;\"></span><span class=\"accent-body\" style=\"left:-0.0833em;\"><span class=\"mord\">˙</span></span></span></span></span></span></span></span></span></span><span class=\"vlist-s\">​</span></span><span class=\"vlist-r\"><span class=\"vlist\" style=\"height:2em;\"><span></span></span></span></span></span><span class=\"col-align-l\"><span class=\"vlist-t vlist-t2\"><span class=\"vlist-r\"><span class=\"vlist\" style=\"height:2.5em;\"><span style=\"top:-4.66em;\"><span class=\"pstrut\" style=\"height:3em;\"></span><span class=\"mord\"><span class=\"mord\"></span><span class=\"mspace\" style=\"margin-right:0.2778em;\"></span><span class=\"mrel\">=</span><span class=\"mspace\" style=\"margin-right:0.2778em;\"></span><span class=\"mord mathnormal\" style=\"margin-right:0.03588em;\">σ</span><span class=\"mopen\">(</span><span class=\"mord mathnormal\" style=\"margin-right:0.03588em;\">y</span><span class=\"mspace\" style=\"margin-right:0.2222em;\"></span><span class=\"mbin\">−</span><span class=\"mspace\" style=\"margin-right:0.2222em;\"></span><span class=\"mord mathnormal\">x</span><span class=\"mclose\">)</span></span></span><span style=\"top:-3.16em;\"><span class=\"pstrut\" style=\"height:3em;\"></span><span class=\"mord\"><span class=\"mord\"></span><span class=\"mspace\" style=\"margin-right:0.2778em;\"></span><span class=\"mrel\">=</span><span class=\"mspace\" style=\"margin-right:0.2778em;\"></span><span class=\"mord mathnormal\">ρ</span><span class=\"mord mathnormal\">x</span><span class=\"mspace\" style=\"margin-right:0.2222em;\"></span><span class=\"mbin\">−</span><span class=\"mspace\" style=\"margin-right:0.2222em;\"></span><span class=\"mord mathnormal\" style=\"margin-right:0.03588em;\">y</span><span class=\"mspace\" style=\"margin-right:0.2222em;\"></span><span class=\"mbin\">−</span><span class=\"mspace\" style=\"margin-right:0.2222em;\"></span><span class=\"mord mathnormal\">x</span><span class=\"mord mathnormal\" style=\"margin-right:0.04398em;\">z</span></span></span><span style=\"top:-1.66em;\"><span class=\"pstrut\" style=\"height:3em;\"></span><span class=\"mord\"><span class=\"mord\"></span><span class=\"mspace\" style=\"margin-right:0.2778em;\"></span><span class=\"mrel\">=</span><span class=\"mspace\" style=\"margin-right:0.2778em;\"></span><span class=\"mord\">−</span><span class=\"mord mathnormal\" style=\"margin-right:0.05278em;\">β</span><span class=\"mord mathnormal\" style=\"margin-right:0.04398em;\">z</span><span class=\"mspace\" style=\"margin-right:0.2222em;\"></span><span class=\"mbin\">+</span><span class=\"mspace\" style=\"margin-right:0.2222em;\"></span><span class=\"mord mathnormal\">x</span><span class=\"mord mathnormal\" style=\"margin-right:0.03588em;\">y</span></span></span></span><span class=\"vlist-s\">​</span></span><span class=\"vlist-r\"><span class=\"vlist\" style=\"height:2em;\"><span></span></span></span></span></span></span></span><span class=\"tag\"><span class=\"vlist-t vlist-t2\"><span class=\"vlist-r\"><span class=\"vlist\" style=\"height:2.5em;\"><span style=\"top:-4.5em;\"><span class=\"pstrut\" style=\"height:2.84em;\"></span><span class=\"eqn-num\"></span></span><span style=\"top:-3em;\"><span class=\"pstrut\" style=\"height:2.84em;\"></span><span class=\"eqn-num\"></span></span><span style=\"top:-1.5em;\"><span class=\"pstrut\" style=\"height:2.84em;\"></span><span class=\"eqn-num\"></span></span></span><span class=\"vlist-s\">​</span></span><span class=\"vlist-r\"><span class=\"vlist\" style=\"height:2em;\"><span></span></span></span></span></span></span></span></span>","enumerator":"1","key":"SmfWIVT6hC"}],"key":"iQdDiPk0Eq"},{"type":"block","kind":"notebook-content","children":[{"type":"paragraph","position":{"start":{"line":1,"column":1},"end":{"line":1,"column":1}},"children":[{"type":"text","value":"Check out ","position":{"start":{"line":1,"column":1},"end":{"line":1,"column":1}},"key":"CgcDTOZW4E"},{"type":"link","url":"https://www.markdownguide.org/basic-syntax/","position":{"start":{"line":1,"column":1},"end":{"line":1,"column":1}},"children":[{"type":"strong","position":{"start":{"line":1,"column":1},"end":{"line":1,"column":1}},"children":[{"type":"text","value":"any number of helpful Markdown resources","position":{"start":{"line":1,"column":1},"end":{"line":1,"column":1}},"key":"UZNxfDtvWv"}],"key":"Hw4ATidzIn"}],"urlSource":"https://www.markdownguide.org/basic-syntax/","key":"KJVRxvbe4M"},{"type":"text","value":" for further customizing your notebooks and the ","position":{"start":{"line":1,"column":1},"end":{"line":1,"column":1}},"key":"i1UJnS0ko3"},{"type":"link","url":"https://jupyter-notebook.readthedocs.io/en/stable/examples/Notebook/Working%20With%20Markdown%20Cells.html","position":{"start":{"line":1,"column":1},"end":{"line":1,"column":1}},"children":[{"type":"strong","position":{"start":{"line":1,"column":1},"end":{"line":1,"column":1}},"children":[{"type":"text","value":"Jupyter docs","position":{"start":{"line":1,"column":1},"end":{"line":1,"column":1}},"key":"RcMv7zB6PC"}],"key":"q14Vry4Ruw"}],"urlSource":"https://jupyter-notebook.readthedocs.io/en/stable/examples/Notebook/Working%20With%20Markdown%20Cells.html","key":"YzE0WsMEua"},{"type":"text","value":" for Jupyter-specific formatting information. Don’t hesitate to ask questions if you have problems getting it to look ","position":{"start":{"line":1,"column":1},"end":{"line":1,"column":1}},"key":"sHqPX6OntF"},{"type":"emphasis","position":{"start":{"line":1,"column":1},"end":{"line":1,"column":1}},"children":[{"type":"text","value":"just right","position":{"start":{"line":1,"column":1},"end":{"line":1,"column":1}},"key":"hRvvQ6Xxn5"}],"key":"PUuYbqt07P"},{"type":"text","value":".","position":{"start":{"line":1,"column":1},"end":{"line":1,"column":1}},"key":"QIyGEpcRxb"}],"key":"stI3tHmTTU"}],"key":"VyNnJiYBfO"},{"type":"block","kind":"notebook-content","children":[{"type":"heading","depth":2,"position":{"start":{"line":1,"column":1},"end":{"line":1,"column":1}},"children":[{"type":"text","value":"Last Section","position":{"start":{"line":1,"column":1},"end":{"line":1,"column":1}},"key":"LxbUlwsHIi"}],"identifier":"last-section","label":"Last Section","html_id":"last-section","implicit":true,"key":"t6xK0KVuMw"},{"type":"paragraph","position":{"start":{"line":3,"column":1},"end":{"line":3,"column":1}},"children":[{"type":"text","value":"If you’re comfortable, and as we briefly used for our embedded logo up top, you can embed raw html into Jupyter Markdown cells (edit to see):","position":{"start":{"line":3,"column":1},"end":{"line":3,"column":1}},"key":"RG7aBnNZdx"}],"key":"JwMQWNZPby"}],"key":"QtP2IbdMSn"},{"type":"block","kind":"notebook-content","children":[{"type":"div","class":"admonition alert alert-info","children":[{"type":"paragraph","children":[{"type":"text","value":"Info","key":"dzGRgZyI7d"}],"key":"TJhZQ646fO"},{"type":"text","value":"Your relevant information here!","key":"rLl6ysIfBx"}],"key":"HqqIUR3mlA"}],"key":"yKsSs18tJe"},{"type":"block","kind":"notebook-content","children":[{"type":"paragraph","position":{"start":{"line":1,"column":1},"end":{"line":1,"column":1}},"children":[{"type":"text","value":"Feel free to copy this around and edit or play around with yourself. Some other ","position":{"start":{"line":1,"column":1},"end":{"line":1,"column":1}},"key":"gmIDC92SfR"},{"type":"inlineCode","value":"admonitions","position":{"start":{"line":1,"column":1},"end":{"line":1,"column":1}},"key":"m4teb7ZvQZ"},{"type":"text","value":" you can put in:","position":{"start":{"line":1,"column":1},"end":{"line":1,"column":1}},"key":"JXEoFd8o01"}],"key":"pT6tlm2OA3"}],"key":"d16R9vNIQP"},{"type":"block","kind":"notebook-content","children":[{"type":"div","class":"admonition alert alert-success","children":[{"type":"paragraph","children":[{"type":"text","value":"Success","key":"J1PIAmNizs"}],"key":"dErHHdBeyQ"},{"type":"text","value":"We got this done after all!","key":"hABbLPFiD2"}],"key":"aHCECGmtkL"}],"key":"oNCow73wpa"},{"type":"block","kind":"notebook-content","children":[{"type":"div","class":"admonition alert alert-warning","children":[{"type":"paragraph","children":[{"type":"text","value":"Warning","key":"mS92gKLku1"}],"key":"h5cuYHGl2y"},{"type":"text","value":"Be careful!","key":"qrsbRFDd1i"}],"key":"Iyr4WrV1k2"}],"key":"unGRLMBpon"},{"type":"block","kind":"notebook-content","children":[{"type":"div","class":"admonition alert alert-danger","children":[{"type":"paragraph","children":[{"type":"text","value":"Danger","key":"bSW0FEX04a"}],"key":"PZ0yrsh68l"},{"type":"text","value":"Scary stuff be here.","key":"RtO5tPK4V0"}],"key":"xNDuYkFd9O"}],"key":"mDprrUFzId"},{"type":"block","kind":"notebook-content","children":[{"type":"paragraph","position":{"start":{"line":1,"column":1},"end":{"line":1,"column":1}},"children":[{"type":"text","value":"We also suggest checking out Jupyter Book’s ","position":{"start":{"line":1,"column":1},"end":{"line":1,"column":1}},"key":"YBO1WBeShA"},{"type":"link","url":"https://jupyterbook.org/content/metadata.html#jupyter-cell-tags","position":{"start":{"line":1,"column":1},"end":{"line":1,"column":1}},"children":[{"type":"text","value":"brief demonstration","position":{"start":{"line":1,"column":1},"end":{"line":1,"column":1}},"key":"harARuSXWa"}],"urlSource":"https://jupyterbook.org/content/metadata.html#jupyter-cell-tags","key":"qXBlCInItT"},{"type":"text","value":" on adding cell tags to your cells in Jupyter Notebook, Lab, or manually. Using these cell tags can allow you to ","position":{"start":{"line":1,"column":1},"end":{"line":1,"column":1}},"key":"yld7SiPEs1"},{"type":"link","url":"https://jupyterbook.org/interactive/hiding.html","position":{"start":{"line":1,"column":1},"end":{"line":1,"column":1}},"children":[{"type":"text","value":"customize","position":{"start":{"line":1,"column":1},"end":{"line":1,"column":1}},"key":"uH4zPzvBAP"}],"urlSource":"https://jupyterbook.org/interactive/hiding.html","key":"mt5E929npn"},{"type":"text","value":" how your code content is displayed and even ","position":{"start":{"line":1,"column":1},"end":{"line":1,"column":1}},"key":"WW0smhv6YU"},{"type":"link","url":"https://jupyterbook.org/content/execute.html#dealing-with-code-that-raises-errors","position":{"start":{"line":1,"column":1},"end":{"line":1,"column":1}},"children":[{"type":"text","value":"demonstrate errors","position":{"start":{"line":1,"column":1},"end":{"line":1,"column":1}},"key":"hwqvLx5Eza"}],"urlSource":"https://jupyterbook.org/content/execute.html#dealing-with-code-that-raises-errors","key":"G4UOV8Ow1a"},{"type":"text","value":" without altogether crashing our loyal army of machines!","position":{"start":{"line":1,"column":1},"end":{"line":1,"column":1}},"key":"RDUoIbYA4I"}],"key":"c8jiAnYDGy"}],"key":"hGWsk0Ny7G"},{"type":"block","kind":"notebook-content","children":[{"type":"thematicBreak","position":{"start":{"line":1,"column":1},"end":{"line":1,"column":1}},"key":"iecWNKSuCh"}],"key":"bJvohhRyhf"},{"type":"block","kind":"notebook-content","children":[{"type":"heading","depth":2,"position":{"start":{"line":1,"column":1},"end":{"line":1,"column":1}},"children":[{"type":"text","value":"Summary","position":{"start":{"line":1,"column":1},"end":{"line":1,"column":1}},"key":"oA8ca5KwmV"}],"identifier":"summary","label":"Summary","html_id":"summary","implicit":true,"key":"zyLaDKTzyD"},{"type":"paragraph","position":{"start":{"line":2,"column":1},"end":{"line":2,"column":1}},"children":[{"type":"text","value":"Add one final ","position":{"start":{"line":2,"column":1},"end":{"line":2,"column":1}},"key":"YnK4RFWPrR"},{"type":"inlineCode","value":"---","position":{"start":{"line":2,"column":1},"end":{"line":2,"column":1}},"key":"H9B61gWGn4"},{"type":"text","value":" marking the end of your body of content, and then conclude with a brief single paragraph summarizing at a high level the key pieces that were learned and how they tied to your objectives. Look to reiterate what the most important takeaways were.","position":{"start":{"line":2,"column":1},"end":{"line":2,"column":1}},"key":"CpZwhz3Uhn"}],"key":"rfNziAxTI5"},{"type":"heading","depth":3,"position":{"start":{"line":4,"column":1},"end":{"line":4,"column":1}},"children":[{"type":"text","value":"What’s next?","position":{"start":{"line":4,"column":1},"end":{"line":4,"column":1}},"key":"qzZHSadVmF"}],"identifier":"whats-next","label":"What’s next?","html_id":"whats-next","implicit":true,"key":"gBTmQwvN0r"},{"type":"paragraph","position":{"start":{"line":5,"column":1},"end":{"line":5,"column":1}},"children":[{"type":"text","value":"Let Jupyter book tie this to the next (sequential) piece of content that people could move on to down below and in the sidebar. However, if this page uniquely enables your reader to tackle other nonsequential concepts throughout this book, or even external content, link to it here!","position":{"start":{"line":5,"column":1},"end":{"line":5,"column":1}},"key":"baJRVHjZyt"}],"key":"wOqM05i8Eb"}],"key":"ejkgEsz6Lj"},{"type":"block","kind":"notebook-content","children":[{"type":"heading","depth":2,"position":{"start":{"line":1,"column":1},"end":{"line":1,"column":1}},"children":[{"type":"text","value":"Resources and references","position":{"start":{"line":1,"column":1},"end":{"line":1,"column":1}},"key":"fzvyd3RXfh"}],"identifier":"resources-and-references","label":"Resources and references","html_id":"resources-and-references","implicit":true,"key":"ln4oJsxjqA"},{"type":"paragraph","position":{"start":{"line":2,"column":1},"end":{"line":2,"column":1}},"children":[{"type":"text","value":"Finally, be rigorous in your citations and references as necessary. Give credit where credit is due. Also, feel free to link to relevant external material, further reading, documentation, etc. Then you’re done! Give yourself a quick review, a high five, and send us a pull request. A few final notes:","position":{"start":{"line":2,"column":1},"end":{"line":2,"column":1}},"key":"jbYx6aiaPa"}],"key":"LEhWchzZe1"},{"type":"list","ordered":false,"spread":false,"position":{"start":{"line":3,"column":1},"end":{"line":8,"column":1}},"children":[{"type":"listItem","spread":true,"position":{"start":{"line":3,"column":1},"end":{"line":3,"column":1}},"children":[{"type":"inlineCode","value":"Kernel > Restart Kernel and Run All Cells...","position":{"start":{"line":3,"column":1},"end":{"line":3,"column":1}},"key":"qOFtwWc3Q5"},{"type":"text","value":" to confirm that your notebook will cleanly run from start to finish","position":{"start":{"line":3,"column":1},"end":{"line":3,"column":1}},"key":"N29VR9BgC3"}],"key":"mGAlx8YH2v"},{"type":"listItem","spread":true,"position":{"start":{"line":4,"column":1},"end":{"line":4,"column":1}},"children":[{"type":"inlineCode","value":"Kernel > Restart Kernel and Clear All Outputs...","position":{"start":{"line":4,"column":1},"end":{"line":4,"column":1}},"key":"tDUpzDDaTt"},{"type":"text","value":" before committing your notebook, our machines will do the heavy lifting","position":{"start":{"line":4,"column":1},"end":{"line":4,"column":1}},"key":"VGdyjZCFDI"}],"key":"Zu3P4TG9Di"},{"type":"listItem","spread":true,"position":{"start":{"line":5,"column":1},"end":{"line":5,"column":1}},"children":[{"type":"text","value":"Take credit! Provide author contact information if you’d like; if so, consider adding information here at the bottom of your notebook","position":{"start":{"line":5,"column":1},"end":{"line":5,"column":1}},"key":"TqneuJ99qm"}],"key":"eGBfpUkfqt"},{"type":"listItem","spread":true,"position":{"start":{"line":6,"column":1},"end":{"line":6,"column":1}},"children":[{"type":"text","value":"Give credit! Attribute appropriate authorship for referenced code, information, images, etc.","position":{"start":{"line":6,"column":1},"end":{"line":6,"column":1}},"key":"ED7d7BjIdw"}],"key":"IDPpAoet8L"},{"type":"listItem","spread":true,"position":{"start":{"line":7,"column":1},"end":{"line":8,"column":1}},"children":[{"type":"text","value":"Only include what you’re legally allowed: ","position":{"start":{"line":7,"column":1},"end":{"line":7,"column":1}},"key":"qg7dkeyHUL"},{"type":"strong","position":{"start":{"line":7,"column":1},"end":{"line":7,"column":1}},"children":[{"type":"text","value":"no copyright infringement or plagiarism","position":{"start":{"line":7,"column":1},"end":{"line":7,"column":1}},"key":"o3JfUw2rP6"}],"key":"QHECO1HyJy"}],"key":"g3tvbLQHdS"}],"key":"tT6MJBPqtN"},{"type":"paragraph","position":{"start":{"line":9,"column":1},"end":{"line":9,"column":1}},"children":[{"type":"text","value":"Thank you for your contribution!","position":{"start":{"line":9,"column":1},"end":{"line":9,"column":1}},"key":"r5gYBZuijx"}],"key":"d9VFnv6A49"}],"key":"ynW3vJ0yLH"}],"key":"p51eRR7PcZ"},"references":{"cite":{"order":[],"data":{}}},"footer":{"navigation":{"prev":{"title":"Boundary Conditions","url":"/notebooks/config/boundary-conditions","group":"Coordinates and Initial/Boundary Conditions"},"next":{"title":"Model Assessment and Tradeoffs","url":"/notebooks/summary/assessment","group":"Bringing It All Together"}}},"domain":"http://localhost:3000"}